pck_tylerradke/__init__.py
pck_tylerradke/mod.py
pck_tylerradke-0.0.1.dist-info/METADATA
pck_tylerradke-0.0.1.dist-info/WHEEL
pck_tylerradke-0.0.1.dist-info/RECORD
